README.md
setup.cfg
setup.py
Flask_PynamoDB.egg-info/PKG-INFO
Flask_PynamoDB.egg-info/SOURCES.txt
Flask_PynamoDB.egg-info/dependency_links.txt
Flask_PynamoDB.egg-info/not-zip-safe
Flask_PynamoDB.egg-info/requires.txt
Flask_PynamoDB.egg-info/top_level.txt
flask_pynamodb/__init__.py
flask_pynamodb/model.py