Metadata-Version: 2.1
Name: Flask-PynamoDB
Version: 0.0.2
Summary: Flask-PynamoDB is an extension for integrating with PynamoDB
Home-page: https://github.com/bl4ckst0ne/flask-pynamodb
Author: bl4ckst0ne
Author-email: bl4ckst0ne1@gmail.com
License: MIT
Platform: any
Classifier: Environment :: Web Environment
Classifier: Intended Audience :: Developers
Classifier: License :: OSI Approved :: MIT License
Classifier: Operating System :: OS Independent
Classifier: Programming Language :: Python
Classifier: Programming Language :: Python :: 3 :: Only
Classifier: Topic :: Internet :: WWW/HTTP :: Dynamic Content
Classifier: Topic :: Software Development :: Libraries :: Python Modules
